setup.py
ryClasses/__init__.py
ryClasses.egg-info/PKG-INFO
ryClasses.egg-info/SOURCES.txt
ryClasses.egg-info/dependency_links.txt
ryClasses.egg-info/top_level.txt