Metadata-Version: 1.1
Name: ryClasses
Version: 0.0.1
Summary: 若宇工作室的类库
Home-page: https://github.com/
Author: Ruoyu Wang
Author-email: wangkang@139.com
License: UNKNOWN
Platform: UNKNOWN
Classifier: Programming Language :: Python :: 3
Classifier: License :: OSI Approved :: MIT License
Classifier: Operating System :: OS Independent
